{
  "$schema": "https://ui.shadcn.com/schema/registry-item.json",
  "name": "weather-dashboard",
  "type": "registry:component",
  "title": "Painel de Clima",
  "description": "Painel de clima imersivo com gráficos horários, previsão semanal e alertas de qualidade do ar ao vivo",
  "registryDependencies": [
    "badge",
    "button"
  ],
  "dependencies": [
    "framer-motion",
    "lucide-react",
    "react"
  ],
  "files": [
    {
      "path": "components/components/weather/weather-dashboard.tsx",
      "content": "\"use client\";\r\n\r\nimport type React from \"react\";\r\n\r\nimport { useMemo } from \"react\";\r\nimport { motion, type Variants } from \"framer-motion\";\r\nimport {\r\n  Area,\r\n  AreaChart,\r\n  CartesianGrid,\r\n  ResponsiveContainer,\r\n  Tooltip,\r\n  XAxis,\r\n} from \"recharts\";\r\nimport { Badge } from \"@/components/ui/badge\";\r\nimport { Button } from \"@/components/ui/button\";\r\nimport {\r\n  CalendarDays,\r\n  Cloud,\r\n  CloudLightning,\r\n  CloudRain,\r\n  Droplets,\r\n  Gauge,\r\n  LucideIcon,\r\n  MapPin,\r\n  RefreshCcw,\r\n  Sun,\r\n  Sunrise,\r\n  Sunset,\r\n  Thermometer,\r\n  Umbrella,\r\n  Wind,\r\n} from \"lucide-react\";\r\n\r\ntype WeatherCondition = \"sunny\" | \"rain\" | \"cloudy\" | \"storm\";\r\n\r\ntype HourlyForecast = {\r\n  time: string;\r\n  temperature: number;\r\n  feelsLike: number;\r\n  precipitationChance: number;\r\n  windSpeed: number;\r\n  condition: WeatherCondition;\r\n};\r\n\r\ntype WeeklyForecast = {\r\n  day: string;\r\n  high: number;\r\n  low: number;\r\n  precipitationChance: number;\r\n  condition: WeatherCondition;\r\n};\r\n\r\ntype WeatherMetric = {\r\n  label: string;\r\n  value: string;\r\n  description: string;\r\n  icon: LucideIcon;\r\n};\r\n\r\ntype AirQualityMetric = {\r\n  label: string;\r\n  value: string;\r\n  status: string;\r\n  description: string;\r\n};\r\n\r\ntype AlertSeverity = \"Advisory\" | \"Watch\" | \"Warning\";\r\n\r\ntype WeatherAlert = {\r\n  title: string;\r\n  description: string;\r\n  severity: AlertSeverity;\r\n  icon: LucideIcon;\r\n};\r\n\r\ntype WeatherData = {\r\n  location: string;\r\n  updatedAt: string;\r\n  current: {\r\n    temperature: number;\r\n    feelsLike: number;\r\n    summary: string;\r\n    condition: WeatherCondition;\r\n    humidity: number;\r\n    precipitationChance: number;\r\n    windSpeed: number;\r\n    pressure: number;\r\n    sunrise: string;\r\n    sunset: string;\r\n  };\r\n  hourly: HourlyForecast[];\r\n  weekly: WeeklyForecast[];\r\n  airQuality: AirQualityMetric[];\r\n  alerts: WeatherAlert[];\r\n};\r\n\r\nconst STATIC_WEATHER_DATA: WeatherData = {\r\n  location: \"San Francisco, CA\",\r\n  updatedAt: \"2024-07-12T16:00:00.000Z\",\r\n  current: {\r\n    temperature: 64,\r\n    feelsLike: 62,\r\n    summary: \"Mostly sunny with a coastal breeze\",\r\n    condition: \"sunny\",\r\n    humidity: 62,\r\n    precipitationChance: 15,\r\n    windSpeed: 12,\r\n    pressure: 1016,\r\n    sunrise: \"2024-07-12T13:58:00.000Z\",\r\n    sunset: \"2024-07-13T03:33:00.000Z\",\r\n  },\r\n  hourly: [\r\n    {\r\n      time: \"2024-07-12T16:00:00.000Z\",\r\n      temperature: 60,\r\n      feelsLike: 59,\r\n      precipitationChance: 10,\r\n      windSpeed: 10,\r\n      condition: \"sunny\",\r\n    },\r\n    {\r\n      time: \"2024-07-12T17:00:00.000Z\",\r\n      temperature: 61,\r\n      feelsLike: 60,\r\n      precipitationChance: 12,\r\n      windSpeed: 11,\r\n      condition: \"sunny\",\r\n    },\r\n    {\r\n      time: \"2024-07-12T18:00:00.000Z\",\r\n      temperature: 62,\r\n      feelsLike: 61,\r\n      precipitationChance: 12,\r\n      windSpeed: 12,\r\n      condition: \"sunny\",\r\n    },\r\n    {\r\n      time: \"2024-07-12T19:00:00.000Z\",\r\n      temperature: 63,\r\n      feelsLike: 62,\r\n      precipitationChance: 15,\r\n      windSpeed: 13,\r\n      condition: \"sunny\",\r\n    },\r\n    {\r\n      time: \"2024-07-12T20:00:00.000Z\",\r\n      temperature: 64,\r\n      feelsLike: 63,\r\n      precipitationChance: 18,\r\n      windSpeed: 14,\r\n      condition: \"sunny\",\r\n    },\r\n    {\r\n      time: \"2024-07-12T21:00:00.000Z\",\r\n      temperature: 65,\r\n      feelsLike: 64,\r\n      precipitationChance: 20,\r\n      windSpeed: 14,\r\n      condition: \"sunny\",\r\n    },\r\n    {\r\n      time: \"2024-07-12T22:00:00.000Z\",\r\n      temperature: 66,\r\n      feelsLike: 65,\r\n      precipitationChance: 20,\r\n      windSpeed: 13,\r\n      condition: \"sunny\",\r\n    },\r\n    {\r\n      time: \"2024-07-12T23:00:00.000Z\",\r\n      temperature: 65,\r\n      feelsLike: 64,\r\n      precipitationChance: 18,\r\n      windSpeed: 12,\r\n      condition: \"sunny\",\r\n    },\r\n    {\r\n      time: \"2024-07-13T00:00:00.000Z\",\r\n      temperature: 63,\r\n      feelsLike: 62,\r\n      precipitationChance: 15,\r\n      windSpeed: 11,\r\n      condition: \"cloudy\",\r\n    },\r\n    {\r\n      time: \"2024-07-13T01:00:00.000Z\",\r\n      temperature: 61,\r\n      feelsLike: 60,\r\n      precipitationChance: 12,\r\n      windSpeed: 10,\r\n      condition: \"cloudy\",\r\n    },\r\n    {\r\n      time: \"2024-07-13T02:00:00.000Z\",\r\n      temperature: 59,\r\n      feelsLike: 58,\r\n      precipitationChance: 10,\r\n      windSpeed: 9,\r\n      condition: \"cloudy\",\r\n    },\r\n    {\r\n      time: \"2024-07-13T03:00:00.000Z\",\r\n      temperature: 58,\r\n      feelsLike: 57,\r\n      precipitationChance: 8,\r\n      windSpeed: 8,\r\n      condition: \"cloudy\",\r\n    },\r\n  ],\r\n  weekly: [\r\n    {\r\n      day: \"2024-07-12\",\r\n      high: 66,\r\n      low: 56,\r\n      precipitationChance: 20,\r\n      condition: \"sunny\",\r\n    },\r\n    {\r\n      day: \"2024-07-13\",\r\n      high: 65,\r\n      low: 55,\r\n      precipitationChance: 25,\r\n      condition: \"sunny\",\r\n    },\r\n    {\r\n      day: \"2024-07-14\",\r\n      high: 64,\r\n      low: 54,\r\n      precipitationChance: 30,\r\n      condition: \"cloudy\",\r\n    },\r\n    {\r\n      day: \"2024-07-15\",\r\n      high: 63,\r\n      low: 54,\r\n      precipitationChance: 40,\r\n      condition: \"cloudy\",\r\n    },\r\n    {\r\n      day: \"2024-07-16\",\r\n      high: 62,\r\n      low: 53,\r\n      precipitationChance: 45,\r\n      condition: \"rain\",\r\n    },\r\n    {\r\n      day: \"2024-07-17\",\r\n      high: 64,\r\n      low: 54,\r\n      precipitationChance: 30,\r\n      condition: \"sunny\",\r\n    },\r\n    {\r\n      day: \"2024-07-18\",\r\n      high: 67,\r\n      low: 55,\r\n      precipitationChance: 15,\r\n      condition: \"sunny\",\r\n    },\r\n  ],\r\n  airQuality: [\r\n    {\r\n      label: \"US AQI\",\r\n      value: \"42\",\r\n      status: \"Bom\",\r\n      description:\r\n        \"Ar costeiro limpo com matéria particulada mínima detectada.\",\r\n    },\r\n    {\r\n      label: \"PM2.5\",\r\n      value: \"8.6 µg/m³\",\r\n      status: \"Níveis baixos de particulados\",\r\n      description:\r\n        \"Particulados finos permanecem bem abaixo dos limites diários.\",\r\n    },\r\n    {\r\n      label: \"Índice de Poeira\",\r\n      value: \"18.4 µg/m³\",\r\n      status: \"Poeira mínima\",\r\n      description:\r\n        \"Influência marinha mantém concentrações de poeira aérea baixas.\",\r\n    },\r\n  ],\r\n  alerts: [\r\n    {\r\n      title: \"Brisa onshore suave continua\",\r\n      description:\r\n        \"Espere um vento oeste suave durante a tarde com águas da baía agitadas.\",\r\n      severity: \"Aviso\",\r\n      icon: Wind,\r\n    },\r\n    {\r\n      title: \"Baixa chance de chuva durante o fim de semana\",\r\n      description:\r\n        \"Possível névoa esporádica perto da costa no final da noite, mas seco para a maioria dos planos.\",\r\n      severity: \"Observação\",\r\n      icon: Umbrella,\r\n    },\r\n  ],\r\n};\r\n\r\nconst containerVariants: Variants = {\r\n  hidden: { opacity: 0 },\r\n  visible: {\r\n    opacity: 1,\r\n    transition: {\r\n      staggerChildren: 0.1,\r\n      delayChildren: 0.2,\r\n    },\r\n  },\r\n};\r\n\r\nconst itemVariants: Variants = {\r\n  hidden: { opacity: 0, y: 16 },\r\n  visible: {\r\n    opacity: 1,\r\n    y: 0,\r\n    transition: { duration: 0.4, ease: \"easeOut\" },\r\n  },\r\n};\r\n\r\nconst listItemVariants: Variants = {\r\n  hidden: { opacity: 0, y: 12 },\r\n  visible: {\r\n    opacity: 1,\r\n    y: 0,\r\n    transition: { duration: 0.35, ease: \"easeOut\" },\r\n  },\r\n};\r\n\r\nconst SEVERITY_STYLES: Record<AlertSeverity, string> = {\r\n  Advisory: \"bg-blue-500/20 text-blue-600 dark:text-blue-400\",\r\n  Watch: \"bg-amber-500/20 text-amber-600 dark:text-amber-400\",\r\n  Warning: \"bg-red-500/20 text-red-600 dark:text-red-400\",\r\n};\r\n\r\nconst CONDITION_ICONS: Record<WeatherCondition, LucideIcon> = {\r\n  sunny: Sun,\r\n  rain: CloudRain,\r\n  cloudy: Cloud,\r\n  storm: CloudLightning,\r\n};\r\n\r\nfunction formatHour(timestamp: string, timezone?: string) {\r\n  return new Intl.DateTimeFormat(undefined, {\r\n    hour: \"numeric\",\r\n    hour12: true,\r\n    timeZone: timezone,\r\n  }).format(new Date(timestamp));\r\n}\r\n\r\nfunction formatDay(timestamp: string, timezone?: string) {\r\n  return new Intl.DateTimeFormat(undefined, {\r\n    weekday: \"short\",\r\n    timeZone: timezone,\r\n  }).format(new Date(timestamp));\r\n}\r\n\r\nfunction formatTime(timestamp: string, timezone?: string) {\r\n  return new Intl.DateTimeFormat(undefined, {\r\n    hour: \"numeric\",\r\n    minute: \"2-digit\",\r\n    hour12: true,\r\n    timeZone: timezone,\r\n  }).format(new Date(timestamp));\r\n}\r\n\r\nfunction describeHumidity(value: number) {\r\n  if (value >= 70) return \"Humid – expect a touch of mugginess\";\r\n  if (value <= 30) return \"Dry air – hydrate frequently\";\r\n  return \"Comfortable humidity for outdoor plans\";\r\n}\r\n\r\nfunction describeWind(speed: number) {\r\n  if (speed >= 25) return \"Breezy with gusts – secure loose items\";\r\n  if (speed >= 15) return \"Noticeable breeze across the bay\";\r\n  return \"Light winds – calm conditions\";\r\n}\r\n\r\nfunction describePressure(value: number) {\r\n  if (value >= 1020) return \"High pressure holding – skies stay stable\";\r\n  if (value <= 1005) return \"Low pressure developing – expect shifts\";\r\n  return \"Steady pressure – minimal change expected\";\r\n}\r\n\r\nfunction describePrecipitation(chance: number) {\r\n  if (chance >= 60) return \"Keep rain gear handy\";\r\n  if (chance >= 30) return \"Spotty showers possible\";\r\n  return \"Minimal chance of precipitation\";\r\n}\r\n\r\nexport function WeatherDashboard(): React.ReactElement {\r\n  const activeView = \"today\";\r\n  const weatherData = STATIC_WEATHER_DATA;\r\n\r\n  const weatherMetrics = useMemo<WeatherMetric[]>(() => {\r\n    return [\r\n      {\r\n        label: \"Humidity\",\r\n        value: weatherData.current.humidity + \"%\",\r\n        description: describeHumidity(weatherData.current.humidity),\r\n        icon: Droplets,\r\n      },\r\n      {\r\n        label: \"Wind\",\r\n        value: weatherData.current.windSpeed + \" mph\",\r\n        description: describeWind(weatherData.current.windSpeed),\r\n        icon: Wind,\r\n      },\r\n      {\r\n        label: \"Pressure\",\r\n        value: weatherData.current.pressure + \" hPa\",\r\n        description: describePressure(weatherData.current.pressure),\r\n        icon: Gauge,\r\n      },\r\n      {\r\n        label: \"Precipitation\",\r\n        value: weatherData.current.precipitationChance + \"%\",\r\n        description: describePrecipitation(\r\n          weatherData.current.precipitationChance\r\n        ),\r\n        icon: Umbrella,\r\n      },\r\n    ];\r\n  }, [weatherData]);\r\n\r\n  const hourlyChartData = useMemo(\r\n    () =>\r\n      weatherData.hourly.slice(0, 12).map((hour) => ({\r\n        name: formatHour(hour.time),\r\n        temperature: hour.temperature,\r\n        feelsLike: hour.feelsLike,\r\n      })),\r\n    [weatherData]\r\n  );\r\n\r\n  const hourlyForecast = weatherData.hourly.slice(0, 8);\r\n  const weeklyForecast = weatherData.weekly.slice(0, 7);\r\n  const airQualityMetrics = weatherData.airQuality;\r\n  const alerts = weatherData.alerts;\r\n\r\n  const updatedMinutesAgo = useMemo(() => {\r\n    const updatedDate = new Date(weatherData.updatedAt);\r\n    const diffMinutes = Math.floor(\r\n      (Date.now() - updatedDate.getTime()) / (1000 * 60)\r\n    );\r\n    if (diffMinutes <= 1) return \"Updated moments ago\";\r\n    if (diffMinutes < 60) return \"Updated \" + diffMinutes + \" minutes ago\";\r\n    const diffHours = Math.floor(diffMinutes / 60);\r\n    if (diffHours === 1) return \"Updated about an hour ago\";\r\n    return \"Updated \" + diffHours + \" hours ago\";\r\n  }, [weatherData.updatedAt]);\r\n\r\n  return (\r\n    <main className=\"relative min-h-screen overflow-hidden bg-background\">\r\n      <div className=\"relative mx-auto flex min-h-screen flex-col gap-8 py-12 lg:gap-12 lg:py-16\">\r\n        <header className=\"flex flex-col gap-4 md:flex-row md:items-center md:justify-between\">\r\n          <div className=\"space-y-3\">\r\n            <Badge\r\n              variant=\"outline\"\r\n              className=\"inline-flex items-center gap-2 rounded-full border-border/50 bg-background/55 px-4 py-1.5 text-xs uppercase tracking-[0.2em] text-foreground/70 backdrop-blur\"\r\n            >\r\n              <CalendarDays className=\"h-3.5 w-3.5\" aria-hidden=\"true\" />\r\n              7-Day Coastal Outlook\r\n            </Badge>\r\n\r\n            <div>\r\n              <h1 className=\"text-3xl font-semibold tracking-tight text-foreground md:text-4xl\">\r\n                Visão Geral do Clima Costeiro\r\n              </h1>\r\n              <p className=\"mt-2 flex flex-wrap items-center gap-2 text-sm text-foreground/70\">\r\n                <MapPin className=\"h-4 w-4\" aria-hidden=\"true\" />\r\n                {weatherData.location}\r\n                <span aria-live=\"polite\" className=\"text-foreground/50\">\r\n                  · {updatedMinutesAgo}\r\n                </span>\r\n              </p>\r\n            </div>\r\n          </div>\r\n\r\n          <div className=\"flex flex-wrap items-center gap-2\">\r\n            {[\"today\", \"week\", \"radar\"].map((view) => (\r\n              <Button\r\n                key={view}\r\n                type=\"button\"\r\n                variant={view === activeView ? \"default\" : \"ghost\"}\r\n                aria-pressed={view === activeView}\r\n                className=\"rounded-lg px-4 py-2 text-sm uppercase tracking-[0.1em]\"\r\n              >\r\n                {view === \"today\" && \"Hoje\"}\r\n                {view === \"week\" && \"Semana\"}\r\n                {view === \"radar\" && \"Radar\"}\r\n              </Button>\r\n            ))}\r\n            <Button\r\n              type=\"button\"\r\n              variant=\"outline\"\r\n              size=\"sm\"\r\n              onClick={() => undefined}\r\n              className=\"gap-2 rounded-lg text-xs uppercase tracking-[0.15em]\"\r\n            >\r\n              <RefreshCcw className=\"h-4 w-4\" aria-hidden=\"true\" />\r\n              Refresh\r\n            </Button>\r\n          </div>\r\n        </header>\r\n\r\n        <motion.div\r\n          variants={containerVariants}\r\n          initial=\"hidden\"\r\n          animate=\"visible\"\r\n          className=\"grid gap-6 md:gap-8 lg:grid-cols-1\"\r\n          aria-busy={false}\r\n          aria-live=\"polite\"\r\n        >\r\n          <motion.article\r\n            variants={itemVariants}\r\n            className=\"group relative overflow-hidden rounded-2xl border border-border/40 bg-background/60 p-6 backdrop-blur transition-all hover:border-border/60 hover:shadow-lg\"\r\n            role=\"article\"\r\n            aria-label=\"Condições climáticas atuais\"\r\n          >\r\n            <div className=\"absolute inset-0 bg-gradient-to-br from-foreground/[0.04] via-transparent to-transparent opacity-0 transition-opacity duration-300 group-hover:opacity-100 -z-10\" />\r\n\r\n            <div className=\"relative flex flex-col gap-6\">\r\n              <div className=\"flex flex-col gap-3\">\r\n                <div className=\"flex items-center gap-3\">\r\n                  <div className=\"rounded-full border border-border/40 bg-background/60 p-3\">\r\n                    <Sun className=\"h-6 w-6 text-primary\" aria-hidden=\"true\" />\r\n                  </div>\r\n                  <div>\r\n                    <p className=\"text-xs uppercase tracking-[0.2em] text-foreground/70\">\r\n                      Right Now\r\n                    </p>\r\n                    <p className=\"text-sm text-foreground/60\">\r\n                      {weatherData.current.summary}\r\n                    </p>\r\n                  </div>\r\n                </div>\r\n\r\n                <div className=\"flex flex-col gap-1\">\r\n                  <div className=\"flex flex-wrap items-baseline gap-3\">\r\n                    <span className=\"text-5xl font-semibold tracking-tight text-foreground md:text-6xl\">\r\n                      {weatherData.current.temperature}°\r\n                    </span>\r\n                    <span className=\"text-sm text-foreground/60\">\r\n                      Sensação térmica {weatherData.current.feelsLike}°\r\n                    </span>\r\n                  </div>\r\n                  <p className=\"text-sm text-foreground/70\">\r\n                    {\"Chance de chuva \" +\r\n                      weatherData.current.precipitationChance +\r\n                      \"% · Nascer do sol \" +\r\n                      formatTime(weatherData.current.sunrise) +\r\n                      \" · Pôr do sol \" +\r\n                      formatTime(weatherData.current.sunset)}\r\n                  </p>\r\n                </div>\r\n              </div>\r\n\r\n              <motion.div\r\n                role=\"list\"\r\n                className=\"grid grid-cols-1 gap-3 sm:grid-cols-2\"\r\n                initial=\"hidden\"\r\n                animate=\"visible\"\r\n                variants={containerVariants}\r\n              >\r\n                {weatherMetrics.map((metric) => (\r\n                  <motion.div\r\n                    key={metric.label}\r\n                    role=\"listitem\"\r\n                    variants={listItemVariants}\r\n                    whileHover={{ y: -4 }}\r\n                    transition={{ duration: 0.2 }}\r\n                    className=\"flex items-start gap-3 rounded-xl border border-border/30 bg-background/40 p-4 transition-all hover:border-border/50 hover:bg-background/60\"\r\n                  >\r\n                    <span className=\"flex h-10 w-10 items-center justify-center rounded-full border border-border/40 bg-background/60 text-foreground/70\">\r\n                      <metric.icon className=\"h-4 w-4\" aria-hidden=\"true\" />\r\n                    </span>\r\n                    <div className=\"space-y-1\">\r\n                      <p className=\"text-xs font-semibold uppercase tracking-[0.2em] text-foreground/60\">\r\n                        {metric.label}\r\n                      </p>\r\n                      <p className=\"text-lg font-semibold text-foreground\">\r\n                        {metric.value}\r\n                      </p>\r\n                      <p className=\"text-xs text-foreground/60\">\r\n                        {metric.description}\r\n                      </p>\r\n                    </div>\r\n                  </motion.div>\r\n                ))}\r\n              </motion.div>\r\n\r\n              <div className=\"flex flex-col gap-3 rounded-xl border border-border/30 bg-background/30 p-4\">\r\n                <div className=\"flex items-center justify-between text-sm text-foreground/70\">\r\n                  <div className=\"flex items-center gap-2\">\r\n                    <Sunrise className=\"h-4 w-4\" aria-hidden=\"true\" />\r\n                    Nascer do sol\r\n                  </div>\r\n                  <span className=\"text-foreground\">\r\n                    {formatTime(weatherData.current.sunrise)}\r\n                  </span>\r\n                </div>\r\n                <div className=\"flex items-center justify-between text-sm text-foreground/70\">\r\n                  <div className=\"flex items-center gap-2\">\r\n                    <Sunset className=\"h-4 w-4\" aria-hidden=\"true\" />\r\n                    Pôr do sol\r\n                  </div>\r\n                  <span className=\"text-foreground\">\r\n                    {formatTime(weatherData.current.sunset)}\r\n                  </span>\r\n                </div>\r\n              </div>\r\n            </div>\r\n          </motion.article>\r\n\r\n          <motion.article\r\n            variants={itemVariants}\r\n            className=\"group relative overflow-hidden rounded-2xl border border-border/40 bg-background/60 p-6 backdrop-blur transition-all hover:border-border/60 hover:shadow-lg \"\r\n            role=\"article\"\r\n            aria-label=\"Hourly forecast chart\"\r\n          >\r\n            <div className=\"absolute inset-0 bg-gradient-to-br from-foreground/[0.04] via-transparent to-transparent opacity-0 transition-opacity duration-300 group-hover:opacity-100 -z-10\" />\r\n\r\n            <div className=\"relative flex flex-col gap-6\">\r\n              <div className=\"flex flex-wrap items-center justify-between gap-3\">\r\n                <div>\r\n                  <h2 className=\"text-sm font-semibold uppercase tracking-[0.25em] text-foreground\">\r\n                    Hourly Forecast\r\n                  </h2>\r\n                  <p className=\"text-xs text-foreground/60\">\r\n                    Temperature trend and precipitation chance through the\r\n                    evening\r\n                  </p>\r\n                </div>\r\n                <Badge className=\"rounded-full bg-primary/20 text-xs uppercase tracking-[0.2em] text-primary\">\r\n                  Live radar calibrated\r\n                </Badge>\r\n              </div>\r\n\r\n              <div style={{ width: \"100%\", height: 260 }} className=\"relative\">\r\n                <ResponsiveContainer width=\"100%\" height=\"100%\">\r\n                  <AreaChart\r\n                    data={hourlyChartData}\r\n                    margin={{ top: 10, right: 16, left: -20, bottom: 0 }}\r\n                  >\r\n                    <defs>\r\n                      <linearGradient\r\n                        id=\"temperatureGradient\"\r\n                        x1=\"0\"\r\n                        y1=\"0\"\r\n                        x2=\"0\"\r\n                        y2=\"1\"\r\n                      >\r\n                        <stop\r\n                          offset=\"5%\"\r\n                          stopColor=\"hsl(var(--primary))\"\r\n                          stopOpacity={0.45}\r\n                        />\r\n                        <stop\r\n                          offset=\"95%\"\r\n                          stopColor=\"hsl(var(--primary))\"\r\n                          stopOpacity={0.05}\r\n                        />\r\n                      </linearGradient>\r\n                    </defs>\r\n                    <CartesianGrid\r\n                      strokeDasharray=\"3 3\"\r\n                      stroke=\"hsl(var(--border))\"\r\n                      opacity={0.25}\r\n                      vertical={false}\r\n                    />\r\n                    <XAxis\r\n                      dataKey=\"name\"\r\n                      stroke=\"hsl(var(--foreground))\"\r\n                      opacity={0.6}\r\n                      style={{ fontSize: \"11px\" }}\r\n                    />\r\n                    <Tooltip\r\n                      cursor={{ stroke: \"hsl(var(--primary) / 0.3)\" }}\r\n                      contentStyle={{\r\n                        backgroundColor: \"hsl(var(--background) / 0.8)\",\r\n                        border: \"1px solid hsl(var(--border))\",\r\n                        borderRadius: \"12px\",\r\n                        backdropFilter: \"blur(12px)\",\r\n                        padding: \"10px 12px\",\r\n                      }}\r\n                      labelStyle={{\r\n                        color: \"hsl(var(--foreground))\",\r\n                        fontWeight: 600,\r\n                      }}\r\n                      formatter={(value: number, key: string) => [\r\n                        value.toString() + \"°\",\r\n                        key === \"feelsLike\" ? \"Feels like\" : \"Temperature\",\r\n                      ]}\r\n                    />\r\n                    <Area\r\n                      type=\"natural\"\r\n                      dataKey=\"temperature\"\r\n                      stroke=\"hsl(var(--primary))\"\r\n                      strokeWidth={2.5}\r\n                      fill=\"url(#temperatureGradient)\"\r\n                      activeDot={{ r: 5 }}\r\n                    />\r\n                    <Area\r\n                      type=\"natural\"\r\n                      dataKey=\"feelsLike\"\r\n                      stroke=\"hsl(var(--foreground) / 0.4)\"\r\n                      strokeDasharray=\"6 4\"\r\n                      strokeWidth={2}\r\n                      fillOpacity={0}\r\n                      activeDot={{ r: 4 }}\r\n                    />\r\n                  </AreaChart>\r\n                </ResponsiveContainer>\r\n              </div>\r\n\r\n              <motion.ul\r\n                role=\"list\"\r\n                className=\"grid gap-3 sm:grid-cols-2 xl:grid-cols-4\"\r\n                variants={containerVariants}\r\n                initial=\"hidden\"\r\n                animate=\"visible\"\r\n              >\r\n                {hourlyForecast.map((hour) => {\r\n                  const Icon = CONDITION_ICONS[hour.condition];\r\n                  return (\r\n                    <motion.li\r\n                      key={hour.time}\r\n                      role=\"listitem\"\r\n                      variants={listItemVariants}\r\n                      className=\"group/hour flex flex-col gap-2 rounded-xl border border-border/30 bg-background/40 p-4 text-left transition-all hover:border-border/50 hover:bg-background/60\"\r\n                    >\r\n                      <p className=\"text-xs uppercase tracking-[0.2em] text-foreground/60\">\r\n                        {formatHour(hour.time)}\r\n                      </p>\r\n                      <div className=\"flex items-center justify-between\">\r\n                        <span className=\"text-lg font-semibold text-foreground\">\r\n                          {hour.temperature}°\r\n                        </span>\r\n                        <span className=\"text-xs text-foreground/60\">\r\n                          {hour.feelsLike}° feels\r\n                        </span>\r\n                      </div>\r\n                      <div className=\"flex items-center justify-between text-sm text-foreground/70\">\r\n                        <div className=\"flex items-center gap-2\">\r\n                          <span className=\"flex h-8 w-8 items-center justify-center rounded-full border border-border/40 bg-background/50 text-foreground/70\">\r\n                            <Icon className=\"h-4 w-4\" aria-hidden=\"true\" />\r\n                          </span>\r\n                          <span>{hour.windSpeed} mph winds</span>\r\n                        </div>\r\n                        <span className=\"text-xs text-foreground/60\">\r\n                          {hour.precipitationChance}% rain\r\n                        </span>\r\n                      </div>\r\n                    </motion.li>\r\n                  );\r\n                })}\r\n              </motion.ul>\r\n            </div>\r\n          </motion.article>\r\n\r\n          <motion.article\r\n            variants={itemVariants}\r\n            className=\"group relative overflow-hidden rounded-2xl border border-border/40 bg-background/60 p-6 backdrop-blur transition-all hover:border-border/60 hover:shadow-lg \"\r\n            role=\"article\"\r\n            aria-label=\"7 day extended forecast\"\r\n          >\r\n            <div className=\"absolute inset-0 bg-gradient-to-br from-foreground/[0.04] via-transparent to-transparent opacity-0 transition-opacity duration-300 group-hover:opacity-100 -z-10\" />\r\n\r\n            <div className=\"relative flex flex-col gap-6\">\r\n              <div className=\"flex flex-wrap items-center justify-between gap-3\">\r\n                <div>\r\n                  <h2 className=\"text-sm font-semibold uppercase tracking-[0.25em] text-foreground\">\r\n                    Weekly Outlook\r\n                  </h2>\r\n                  <p className=\"text-xs text-foreground/60\">\r\n                    Plan ahead with precipitation risk and temperature swings\r\n                  </p>\r\n                </div>\r\n                <Button\r\n                  variant=\"ghost\"\r\n                  size=\"sm\"\r\n                  className=\"gap-2 rounded-lg text-xs uppercase tracking-[0.15em] text-foreground/70 hover:text-foreground\"\r\n                >\r\n                  Export\r\n                </Button>\r\n              </div>\r\n\r\n              <motion.ul\r\n                role=\"list\"\r\n                className=\"grid gap-3 sm:grid-cols-2 xl:grid-cols-3\"\r\n                initial=\"hidden\"\r\n                animate=\"visible\"\r\n                variants={containerVariants}\r\n              >\r\n                {weeklyForecast.map((day, index) => {\r\n                  const Icon = CONDITION_ICONS[day.condition];\r\n                  return (\r\n                    <motion.li\r\n                      key={day.day + \"-\" + index}\r\n                      role=\"listitem\"\r\n                      variants={listItemVariants}\r\n                      whileHover={{ y: -4 }}\r\n                      transition={{ duration: 0.2 }}\r\n                      className=\"flex flex-col gap-3 rounded-xl border border-border/30 bg-background/40 p-4 transition-all hover:border-border/50 hover:bg-background/60\"\r\n                    >\r\n                      <div className=\"flex items-center justify-between text-sm text-foreground/70\">\r\n                        <span className=\"text-xs uppercase tracking-[0.2em]\">\r\n                          {formatDay(day.day)}\r\n                        </span>\r\n                        <span>{day.precipitationChance}% rain</span>\r\n                      </div>\r\n                      <div className=\"flex items-center justify-between\">\r\n                        <div className=\"flex items-center gap-3\">\r\n                          <span className=\"flex h-10 w-10 items-center justify-center rounded-full border border-border/40 bg-background/50 text-foreground/70\">\r\n                            <Icon className=\"h-5 w-5\" aria-hidden=\"true\" />\r\n                          </span>\r\n                          <div>\r\n                            <p className=\"text-lg font-semibold text-foreground\">\r\n                              {day.high}°\r\n                            </p>\r\n                            <p className=\"text-xs text-foreground/60\">\r\n                              Low {day.low}°\r\n                            </p>\r\n                          </div>\r\n                        </div>\r\n                        <Badge\r\n                          variant=\"outline\"\r\n                          className=\"rounded-full border-border/40 bg-background/50 px-3 py-1 text-[11px] uppercase tracking-[0.15em] text-foreground/60\"\r\n                        >\r\n                          {day.condition === \"sunny\" && \"Clear\"}\r\n                          {day.condition === \"cloudy\" && \"Clouds\"}\r\n                          {day.condition === \"rain\" && \"Showers\"}\r\n                          {day.condition === \"storm\" && \"Storm\"}\r\n                        </Badge>\r\n                      </div>\r\n                    </motion.li>\r\n                  );\r\n                })}\r\n              </motion.ul>\r\n            </div>\r\n          </motion.article>\r\n\r\n          <motion.article\r\n            variants={itemVariants}\r\n            className=\"group relative overflow-hidden rounded-2xl border border-border/40 bg-background/60 p-6 backdrop-blur transition-all hover:border-border/60 hover:shadow-lg\"\r\n            role=\"article\"\r\n            aria-label=\"Air quality and weather alerts\"\r\n          >\r\n            <div className=\"absolute inset-0 bg-gradient-to-br from-foreground/[0.04] via-transparent to-transparent opacity-0 transition-opacity duration-300 group-hover:opacity-100 -z-10\" />\r\n\r\n            <div className=\"relative flex flex-col gap-6\">\r\n              <div className=\"flex flex-wrap items-center justify-between gap-3\">\r\n                <div>\r\n                  <h2 className=\"text-sm font-semibold uppercase tracking-[0.25em] text-foreground\">\r\n                    Air Quality & Alerts\r\n                  </h2>\r\n                  <p className=\"text-xs text-foreground/60\">\r\n                    Live monitoring for coastal neighborhoods\r\n                  </p>\r\n                </div>\r\n                <Badge className=\"rounded-full bg-emerald-500/20 text-xs uppercase tracking-[0.2em] text-emerald-600 dark:text-emerald-400\">\r\n                  {airQualityMetrics[0]?.status ?? \"Stable\"}\r\n                </Badge>\r\n              </div>\r\n\r\n              <motion.ul\r\n                role=\"list\"\r\n                className=\"grid gap-3\"\r\n                initial=\"hidden\"\r\n                animate=\"visible\"\r\n                variants={containerVariants}\r\n              >\r\n                {airQualityMetrics.map((metric) => (\r\n                  <motion.li\r\n                    key={metric.label}\r\n                    role=\"listitem\"\r\n                    variants={listItemVariants}\r\n                    className=\"rounded-xl border border-border/30 bg-background/40 p-4\"\r\n                  >\r\n                    <div className=\"flex items-center justify-between\">\r\n                      <p className=\"text-xs uppercase tracking-[0.2em] text-foreground/60\">\r\n                        {metric.label}\r\n                      </p>\r\n                      <span className=\"text-sm font-semibold text-foreground\">\r\n                        {metric.value}\r\n                      </span>\r\n                    </div>\r\n                    <p className=\"mt-2 text-sm text-foreground/70\">\r\n                      {metric.status}\r\n                    </p>\r\n                    <p className=\"text-xs text-foreground/60\">\r\n                      {metric.description}\r\n                    </p>\r\n                  </motion.li>\r\n                ))}\r\n              </motion.ul>\r\n\r\n              <div>\r\n                <h3 className=\"text-xs font-semibold uppercase tracking-[0.2em] text-foreground/60\">\r\n                  Local alerts\r\n                </h3>\r\n                <motion.ul\r\n                  role=\"list\"\r\n                  className=\"mt-3 space-y-3\"\r\n                  initial=\"hidden\"\r\n                  animate=\"visible\"\r\n                  variants={containerVariants}\r\n                >\r\n                  {alerts.map((alert) => {\r\n                    const Icon = alert.icon;\r\n                    return (\r\n                      <motion.li\r\n                        key={alert.title}\r\n                        role=\"listitem\"\r\n                        variants={listItemVariants}\r\n                        className=\"flex items-start gap-3 rounded-xl border border-border/30 bg-background/40 p-4\"\r\n                      >\r\n                        <span className=\"flex h-10 w-10 items-center justify-center rounded-full border border-border/40 bg-background/60 text-foreground/70\">\r\n                          <Icon className=\"h-5 w-5\" aria-hidden=\"true\" />\r\n                        </span>\r\n                        <div className=\"flex-1 space-y-1\">\r\n                          <div className=\"flex flex-wrap items-center gap-2\">\r\n                            <p className=\"text-sm font-semibold text-foreground\">\r\n                              {alert.title}\r\n                            </p>\r\n                            <span\r\n                              className={\r\n                                SEVERITY_STYLES[alert.severity] +\r\n                                \" rounded-full px-2 py-1 text-[11px] uppercase tracking-[0.15em]\"\r\n                              }\r\n                            >\r\n                              {alert.severity}\r\n                            </span>\r\n                          </div>\r\n                          <p className=\"text-xs text-foreground/60\">\r\n                            {alert.description}\r\n                          </p>\r\n                        </div>\r\n                      </motion.li>\r\n                    );\r\n                  })}\r\n                </motion.ul>\r\n              </div>\r\n            </div>\r\n          </motion.article>\r\n        </motion.div>\r\n      </div>\r\n    </main>\r\n  );\r\n}\r\n",
      "type": "registry:component",
      "target": "components/components/weather/weather-dashboard"
    }
  ]
}